Workbook

Sheet Lumber Yard Dashboard 
H3: Lumber Yard Management Dashboard
H9: Total Inventory | M9: Estimated Inventory Value
H11: =SUM(Table2[Volume (m³)]) -> 85.047675 | M11: =SUM(Table2[Volume (m³)]) * 19000 -> 1615905.8
H16: Customer Receivables | M16: Supplier Payables
H18: =SUM(Table7[Outstanding Balance]) -> 318225 | M18: =SUM(Table8[Outstanding Balance]) -> 907267.61

Sheet Sales
A1: Invoice No. | B1: Date | C1: Customer Name | D1: Customer ID | E1: Wood Type | F1: Category | G1: Width (cm) | H1: Thickness (cm) | I1: Price / m³ | J1: Length (cm) | K1: Quantity | L1: Volume (m³) | M1: Total Amount | N1: Agreed Amount | O1: Paid Amount | P1: Payment Method | Q1: سعر المتر علينا | R1: التكلفة
A2: A-001 | B2: 46174 | C2: custmer 1 | D2: =IF(Table1[[#This Row],[Customer Name]]="", "",_xlfn.XLOOKUP(C2,Table7[Customer Name],Table7[Customer ID]," ")) -> C-015 | E2: Sixth Grade | F2: Boards | G2: 10 | H2: 2.5 | I2: 21500 | J2: 600 | K2: 60 | L2: =IF(OR(Table1[[#This Row],[Quantity]]="",Table1[[#This Row],[Length (cm)]]=""),"",(Table1[[#This Row],[Width (cm)]]/100)*(Table1[[#This Row],[Thickness (cm)]]/100)*(Table1[[#This Row],[Length (cm)]]/100)*Table1[[#This Row],[Quantity]]) -> 0.9 | M2: =IF(Table1[[#This Row],[Volume (m³)]]="","",Table1[[#This Row],[Volume (m³)]]*Table1[[#This Row],[Price / m³]]) -> 19350 | N2: 19350 | O2: 19350 | P2: Cash | Q2: 19125 | R2: =Table1[[#This Row],[سعر المتر علينا]]*Table1[[#This Row],[Volume (m³)]] -> 17212.5
A3: A-002 | B3: 46174 | C3: custmer 2 | D3: =IF(Table1[[#This Row],[Customer Name]]="", "",_xlfn.XLOOKUP(C3,Table7[Customer Name],Table7[Customer ID]," ")) -> C-019 | E3: Shalboard | F3: Boards | G3: 10 | H3: 2.5 | I3: 21000 | J3: 330 | K3: 2 | L3: =IF(OR(Table1[[#This Row],[Quantity]]="",Table1[[#This Row],[Length (cm)]]=""),"",(Table1[[#This Row],[Width (cm)]]/100)*(Table1[[#This Row],[Thickness (cm)]]/100)*(Table1[[#This Row],[Length (cm)]]/100)*Table1[[#This Row],[Quantity]]) -> 0.0165 | M3: =IF(Table1[[#This Row],[Volume (m³)]]="","",Table1[[#This Row],[Volume (m³)]]*Table1[[#This Row],[Price / m³]]) -> 346.5 | N3: 350 | O3: 350 | P3: Cash | Q3: 19125 | R3: =Table1[[#This Row],[سعر المتر علينا]]*Table1[[#This Row],[Volume (m³)]] -> 315.5625
A4: A-002 | B4: 46174 | C4: custmer 2 | D4: =IF(Table1[[#This Row],[Customer Name]]="", "",_xlfn.XLOOKUP(C4,Table7[Customer Name],Table7[Customer ID]," ")) -> C-019 | E4: Shalboard | F4: Boards | G4: 10 | H4: 2.5 | I4: 21000 | J4: 390 | K4: 2 | L4: =IF(OR(Table1[[#This Row],[Quantity]]="",Table1[[#This Row],[Length (cm)]]=""),"",(Table1[[#This Row],[Width (cm)]]/100)*(Table1[[#This Row],[Thickness (cm)]]/100)*(Table1[[#This Row],[Length (cm)]]/100)*Table1[[#This Row],[Quantity]]) -> 0.0195 | M4: =IF(Table1[[#This Row],[Volume (m³)]]="","",Table1[[#This Row],[Volume (m³)]]*Table1[[#This Row],[Price / m³]]) -> 409.5 | N4: 410 | O4: 410 | P4: Cash | Q4: 19125 | R4: =Table1[[#This Row],[سعر المتر علينا]]*Table1[[#This Row],[Volume (m³)]] -> 372.9375
A5: A-002 | B5: 46174 | C5: custmer 2 | D5: =IF(Table1[[#This Row],[Customer Name]]="", "",_xlfn.XLOOKUP(C5,Table7[Customer Name],Table7[Customer ID]," ")) -> C-019 | E5: Shalboard | F5: Boards | G5: 10 | H5: 2.5 | I5: 21000 | J5: 510 | K5: 2 | L5: =IF(OR(Table1[[#This Row],[Quantity]]="",Table1[[#This Row],[Length (cm)]]=""),"",(Table1[[#This Row],[Width (cm)]]/100)*(Table1[[#This Row],[Thickness (cm)]]/100)*(Table1[[#This Row],[Length (cm)]]/100)*Table1[[#This Row],[Quantity]]) -> 0.0255 | M5: =IF(Table1[[#This Row],[Volume (m³)]]="","",Table1[[#This Row],[Volume (m³)]]*Table1[[#This Row],[Price / m³]]) -> 535.5 | N5: 540 | O5: 540 | P5: Cash | Q5: 19125 | R5: =Table1[[#This Row],[سعر المتر علينا]]*Table1[[#This Row],[Volume (m³)]] -> 487.6875
A6: A-003 | B6: 46175 | C6: shawky | D6: =IF(Table1[[#This Row],[Customer Name]]="", "",_xlfn.XLOOKUP(C6,Table7[Customer Name],Table7[Customer ID]," ")) -> C-011 | E6: Shalboard | F6: Battens | G6: 10 | H6: 2.5 | I6: 21000 | J6: 120 | K6: 9 | L6: =IF(OR(Table1[[#This Row],[Quantity]]="",Table1[[#This Row],[Length (cm)]]=""),"",(Table1[[#This Row],[Width (cm)]]/100)*(Table1[[#This Row],[Thickness (cm)]]/100)*(Table1[[#This Row],[Length (cm)]]/100)*Table1[[#This Row],[Quantity]]) -> 0.027 | M6: =IF(Table1[[#This Row],[Volume (m³)]]="","",Table1[[#This Row],[Volume (m³)]]*Table1[[#This Row],[Price / m³]]) -> 567 | N6: 570 | O6: 570 | P6: Cash | Q6: 19125 | R6: =Table1[[#This Row],[سعر المتر علينا]]*Table1[[#This Row],[Volume (m³)]] -> 516.375
A7: A-004 | B7: 46175 | C7: custmer 3 | D7: =IF(Table1[[#This Row],[Customer Name]]="", "",_xlfn.XLOOKUP(C7,Table7[Customer Name],Table7[Customer ID]," ")) -> C-020 | E7: Shalboard | F7: Battens | G7: 10 | H7: 2.5 | I7: 21000 | J7: 120 | K7: 18 | L7: =IF(OR(Table1[[#This Row],[Quantity]]="",Table1[[#This Row],[Length (cm)]]=""),"",(Table1[[#This Row],[Width (cm)]]/100)*(Table1[[#This Row],[Thickness (cm)]]/100)*(Table1[[#This Row],[Length (cm)]]/100)*Table1[[#This Row],[Quantity]]) -> 0.054 | M7: =IF(Table1[[#This Row],[Volume (m³)]]="","",Table1[[#This Row],[Volume (m³)]]*Table1[[#This Row],[Price / m³]]) -> 1134 | N7: 1135 | O7: 1135 | P7: Cash | Q7: 19125 | R7: =Table1[[#This Row],[سعر المتر علينا]]*Table1[[#This Row],[Volume (m³)]] -> 1032.75
A8: A-004 | B8: 46175 | C8: custmer 3 | D8: =IF(Table1[[#This Row],[Customer Name]]="", "",_xlfn.XLOOKUP(C8,Table7[Customer Name],Table7[Customer ID]," ")) -> C-020 | E8: Shalboard | F8: Battens | G8: 10 | H8: 2.5 | I8: 21000 | J8: 150 | K8: 20 | L8: =IF(OR(Table1[[#This Row],[Quantity]]="",Table1[[#This Row],[Length (cm)]]=""),"",(Table1[[#This Row],[Width (cm)]]/100)*(Table1[[#This Row],[Thickness (cm)]]/100)*(Table1[[#This Row],[Length (cm)]]/100)*Table1[[#This Row],[Quantity]]) -> 0.075 | M8: =IF(Table1[[#This Row],[Volume (m³)]]="","",Table1[[#This Row],[Volume (m³)]]*Table1[[#This Row],[Price / m³]]) -> 1575 | N8: 1575 | O8: 1575 | P8: Cash | Q8: 19125 | R8: =Table1[[#This Row],[سعر المتر علينا]]*Table1[[#This Row],[Volume (m³)]] -> 1434.375
A9: A-004 | B9: 46175 | C9: custmer 3 | D9: =IF(Table1[[#This Row],[Customer Name]]="", "",_xlfn.XLOOKUP(C9,Table7[Customer Name],Table7[Customer ID]," ")) -> C-020 | E9: Shalboard | F9: Battens | G9: 10 | H9: 2.5 | I9: 21000 | J9: 180 | K9: 30 | L9: =IF(OR(Table1[[#This Row],[Quantity]]="",Table1[[#This Row],[Length (cm)]]=""),"",(Table1[[#This Row],[Width (cm)]]/100)*(Table1[[#This Row],[Thickness (cm)]]/100)*(Table1[[#This Row],[Length (cm)]]/100)*Table1[[#This Row],[Quantity]]) -> 0.135 | M9: =IF(Table1[[#This Row],[Volume (m³)]]="","",Table1[[#This Row],[Volume (m³)]]*Table1[[#This Row],[Price / m³]]) -> 2835 | N9: 2760 | O9: 2760 | P9: Cash | Q9: 19125 | R9: =Table1[[#This Row],[سعر المتر علينا]]*Table1[[#This Row],[Volume (m³)]] -> 2581.875
A10: A-004 | B10: 46175 | C10: custmer 3 | D10: =IF(Table1[[#This Row],[Customer Name]]="", "",_xlfn.XLOOKUP(C10,Table7[Customer Name],Table7[Customer ID]," ")) -> C-020 | E10: Shalboard | F10: Boards | G10: 10 | H10: 2.5 | I10: 21000 | J10: 270 | K10: 37 | L10: =IF(OR(Table1[[#This Row],[Quantity]]="",Table1[[#This Row],[Length (cm)]]=""),"",(Table1[[#This Row],[Width (cm)]]/100)*(Table1[[#This Row],[Thickness (cm)]]/100)*(Table1[[#This Row],[Length (cm)]]/100)*Table1[[#This Row],[Quantity]]) -> 0.24975 | M10: =IF(Table1[[#This Row],[Volume (m³)]]="","",Table1[[#This Row],[Volume (m³)]]*Table1[[#This Row],[Price / m³]]) -> 5244.75 | N10: 5230 | O10: 5300 | P10: Cash | Q10: 19125 | R10: =Table1[[#This Row],[سعر المتر علينا]]*Table1[[#This Row],[Volume (m³)]] -> 4776.4688
A11: A-004 | B11: 46175 | C11: custmer 3 | D11: =IF(Table1[[#This Row],[Customer Name]]="", "",_xlfn.XLOOKUP(C11,Table7[Customer Name],Table7[Customer ID]," ")) -> C-020 | E11: Shalboard | F11: Boards | G11: 10 | H11: 2.5 | I11: 21000 | J11: 300 | K11: 32 | L11: =IF(OR(Table1[[#This Row],[Quantity]]="",Table1[[#This Row],[Length (cm)]]=""),"",(Table1[[#This Row],[Width (cm)]]/100)*(Table1[[#This Row],[Thickness (cm)]]/100)*(Table1[[#This Row],[Length (cm)]]/100)*Table1[[#This Row],[Quantity]]) -> 0.24 | M11: =IF(Table1[[#This Row],[Volume (m³)]]="","",Table1[[#This Row],[Volume (m³)]]*Table1[[#This Row],[Price / m³]]) -> 5040 | N11: 5100 | O11: 5030 | P11: Cash | Q11: 19125 | R11: =Table1[[#This Row],[سعر المتر علينا]]*Table1[[#This Row],[Volume (m³)]] -> 4590
A12: A-004 | B12: 46175 | C12: custmer 3 | D12: =IF(Table1[[#This Row],[Customer Name]]="", "",_xlfn.XLOOKUP(C12,Table7[Customer Name],Table7[Customer ID]," ")) -> C-020 | E12: Shalboard | F12: Boards | G12: 10 | H12: 2.5 | I12: 21000 | J12: 330 | K12: 30 | L12: =IF(OR(Table1[[#This Row],[Quantity]]="",Table1[[#This Row],[Length (cm)]]=""),"",(Table1[[#This Row],[Width (cm)]]/100)*(Table1[[#This Row],[Thickness (cm)]]/100)*(Table1[[#This Row],[Length (cm)]]/100)*Table1[[#This Row],[Quantity]]) -> 0.2475 | M12: =IF(Table1[[#This Row],[Volume (m³)]]="","",Table1[[#This Row],[Volume (m³)]]*Table1[[#This Row],[Price / m³]]) -> 5197.5 | N12: 5200 | O12: 5200 | P12: Cash | Q12: 19125 | R12: =Table1[[#This Row],[سعر المتر علينا]]*Table1[[#This Row],[Volume (m³)]] -> 4733.4375
A13: A-005 | B13: 46175 | C13: custmer 4 | D13: =IF(Table1[[#This Row],[Customer Name]]="", "",_xlfn.XLOOKUP(C13,Table7[Customer Name],Table7[Customer ID]," ")) -> C-021 | E13: Shalboard | F13: Boards | G13: 10 | H13: 2.5 | I13: 21000 | J13: 360 | K13: 2 | L13: =IF(OR(Table1[[#This Row],[Quantity]]="",Table1[[#This Row],[Length (cm)]]=""),"",(Table1[[#This Row],[Width (cm)]]/100)*(Table1[[#This Row],[Thickness (cm)]]/100)*(Table1[[#This Row],[Length (cm)]]/100)*Table1[[#This Row],[Quantity]]) -> 0.018 | M13: =IF(Table1[[#This Row],[Volume (m³)]]="","",Table1[[#This Row],[Volume (m³)]]*Table1[[#This Row],[Price / m³]]) -> 378 | N13: 390 | O13: 390 | P13: Cash | Q13: 19125 | R13: =Table1[[#This Row],[سعر المتر علينا]]*Table1[[#This Row],[Volume (m³)]] -> 344.25
... A201: A-098 | B201: 46234 | C201: salah eltawel | D201: =IF(Table1[[#This Row],[Customer Name]]="", "",_xlfn.XLOOKUP(C201,Table7[Customer Name],Table7[Customer ID]," ")) -> C-058 | E201: Shalboard | F201: Boards | G201: 10 | H201: 2.5 | I201: 19500 | J201: 210 | K201: 1 | L201: =IF(OR(Table1[[#This Row],[Quantity]]="",Table1[[#This Row],[Length (cm)]]=""),"",(Table1[[#This Row],[Width (cm)]]/100)*(Table1[[#This Row],[Thickness (cm)]]/100)*(Table1[[#This Row],[Length (cm)]]/100)*Table1[[#This Row],[Quantity]]) -> 0.00525 | M201: =IF(Table1[[#This Row],[Volume (m³)]]="","",Table1[[#This Row],[Volume (m³)]]*Table1[[#This Row],[Price / m³]]) -> 102.375 | N201: 110 | O201: 110 | P201: Cash | Q201: 17061 | R201: =Table1[[#This Row],[سعر المتر علينا]]*Table1[[#This Row],[Volume (m³)]] -> 89.57025

Sheet Inventory Movement
A1: Wood Type | B1: Product Form | C1: Width (cm) | D1: Thickness (cm) | E1: Length (cm) | F1: Opening Stock | G1: Sales | H1: Internal Cutting | I1: External Cutting | J1: Purchases | K1: Current Stock | L1: Volume (m³)
A2: Shalboard | B2: Boards | C2: 10 | D2: 2.5 | E2: 210 | F2: 59 | G2: =SUMIFS(Table1[Quantity],Table1[Wood Type],Table2[[#This Row],[Wood Type]],Table1[Category],Table2[[#This Row],[Product Form]],Table1[Width (cm)],Table2[[#This Row],[Width (cm)]],Table1[Thickness (cm)],Table2[[#This Row],[Thickness (cm)]],Table1[Length (cm)],Table2[[#This Row],[Length (cm)]]) -> 79 | H2: =SUMIFS(Table4[Quantity],Table4[Wood Type],'Inventory Movement'!A2,Table4[Product Form],'Inventory Movement'!B2,Table4[Width (cm)],'Inventory Movement'!C2,Table4[Thickness (cm)],'Inventory Movement'!D2,Table4[Length (cm)],'Inventory Movement'!E2,Table4[Movement Type],"In") -> 10 | I2: =SUMIFS(Table4[Quantity],Table4[Wood Type],'Inventory Movement'!A2,Table4[Product Form],'Inventory Movement'!B2,Table4[Width (cm)],'Inventory Movement'!C2,Table4[Thickness (cm)],'Inventory Movement'!D2,Table4[Length (cm)],'Inventory Movement'!E2,Table4[Movement Type],"Out") -> 0 | J2: =SUMIFS(Table5[Quantity],Table5[Wood Type],Table2[[#This Row],[Wood Type]],Table5[Product Form],Table2[[#This Row],[Product Form]],Table5[Width (cm)],Table2[[#This Row],[Width (cm)]],Table5[Thickness (cm)],Table2[[#This Row],[Thickness (cm)]],Table5[Length (cm)],Table2[[#This Row],[Length (cm)]],Table5[Date],">"&DATE(2026,6,5)) -> 91 | K2: =(Table2[[#This Row],[Opening Stock]]+Table2[[#This Row],[Internal Cutting]]+Table2[[#This Row],[Purchases]])-(Table2[[#This Row],[Sales]]+Table2[[#This Row],[External Cutting]]) -> 81 | L2: =(C2/100)*(D2/100)*(E2/100)*Table2[[#This Row],[Current Stock]] -> 0.42525
A3: Shalboard | B3: Boards | C3: 10 | D3: 2.5 | E3: 240 | F3: 24 | G3: =SUMIFS(Table1[Quantity],Table1[Wood Type],Table2[[#This Row],[Wood Type]],Table1[Category],Table2[[#This Row],[Product Form]],Table1[Width (cm)],Table2[[#This Row],[Width (cm)]],Table1[Thickness (cm)],Table2[[#This Row],[Thickness (cm)]],Table1[Length (cm)],Table2[[#This Row],[Length (cm)]]) -> 30 | H3: =SUMIFS(Table4[Quantity],Table4[Wood Type],'Inventory Movement'!A3,Table4[Product Form],'Inventory Movement'!B3,Table4[Width (cm)],'Inventory Movement'!C3,Table4[Thickness (cm)],'Inventory Movement'!D3,Table4[Length (cm)],'Inventory Movement'!E3,Table4[Movement Type],"In") -> 12 | I3: =SUMIFS(Table4[Quantity],Table4[Wood Type],'Inventory Movement'!A3,Table4[Product Form],'Inventory Movement'!B3,Table4[Width (cm)],'Inventory Movement'!C3,Table4[Thickness (cm)],'Inventory Movement'!D3,Table4[Length (cm)],'Inventory Movement'!E3,Table4[Movement Type],"Out") -> 15 | J3: =SUMIFS(Table5[Quantity],Table5[Wood Type],Table2[[#This Row],[Wood Type]],Table5[Product Form],Table2[[#This Row],[Product Form]],Table5[Width (cm)],Table2[[#This Row],[Width (cm)]],Table5[Thickness (cm)],Table2[[#This Row],[Thickness (cm)]],Table5[Length (cm)],Table2[[#This Row],[Length (cm)]],Table5[Date],">"&DATE(2026,6,5)) -> 313 | K3: =(Table2[[#This Row],[Opening Stock]]+Table2[[#This Row],[Internal Cutting]]+Table2[[#This Row],[Purchases]])-(Table2[[#This Row],[Sales]]+Table2[[#This Row],[External Cutting]]) -> 304 | L3: =(C3/100)*(D3/100)*(E3/100)*Table2[[#This Row],[Current Stock]] -> 1.824
A4: Shalboard | B4: Boards | C4: 10 | D4: 2.5 | E4: 270 | F4: 385 | G4: =SUMIFS(Table1[Quantity],Table1[Wood Type],Table2[[#This Row],[Wood Type]],Table1[Category],Table2[[#This Row],[Product Form]],Table1[Width (cm)],Table2[[#This Row],[Width (cm)]],Table1[Thickness (cm)],Table2[[#This Row],[Thickness (cm)]],Table1[Length (cm)],Table2[[#This Row],[Length (cm)]]) -> 796 | H4: =SUMIFS(Table4[Quantity],Table4[Wood Type],'Inventory Movement'!A4,Table4[Product Form],'Inventory Movement'!B4,Table4[Width (cm)],'Inventory Movement'!C4,Table4[Thickness (cm)],'Inventory Movement'!D4,Table4[Length (cm)],'Inventory Movement'!E4,Table4[Movement Type],"In") -> 178 | I4: =SUMIFS(Table4[Quantity],Table4[Wood Type],'Inventory Movement'!A4,Table4[Product Form],'Inventory Movement'!B4,Table4[Width (cm)],'Inventory Movement'!C4,Table4[Thickness (cm)],'Inventory Movement'!D4,Table4[Length (cm)],'Inventory Movement'!E4,Table4[Movement Type],"Out") -> 0 | J4: =SUMIFS(Table5[Quantity],Table5[Wood Type],Table2[[#This Row],[Wood Type]],Table5[Product Form],Table2[[#This Row],[Product Form]],Table5[Width (cm)],Table2[[#This Row],[Width (cm)]],Table5[Thickness (cm)],Table2[[#This Row],[Thickness (cm)]],Table5[Length (cm)],Table2[[#This Row],[Length (cm)]],Table5[Date],">"&DATE(2026,6,5)) -> 249 | K4: =(Table2[[#This Row],[Opening Stock]]+Table2[[#This Row],[Internal Cutting]]+Table2[[#This Row],[Purchases]])-(Table2[[#This Row],[Sales]]+Table2[[#This Row],[External Cutting]]) -> 16 | L4: =(C4/100)*(D4/100)*(E4/100)*Table2[[#This Row],[Current Stock]] -> 0.108
A5: Shalboard | B5: Boards | C5: 10 | D5: 2.5 | E5: 300 | F5: 665 | G5: =SUMIFS(Table1[Quantity],Table1[Wood Type],Table2[[#This Row],[Wood Type]],Table1[Category],Table2[[#This Row],[Product Form]],Table1[Width (cm)],Table2[[#This Row],[Width (cm)]],Table1[Thickness (cm)],Table2[[#This Row],[Thickness (cm)]],Table1[Length (cm)],Table2[[#This Row],[Length (cm)]]) -> 807 | H5: =SUMIFS(Table4[Quantity],Table4[Wood Type],'Inventory Movement'!A5,Table4[Product Form],'Inventory Movement'!B5,Table4[Width (cm)],'Inventory Movement'!C5,Table4[Thickness (cm)],'Inventory Movement'!D5,Table4[Length (cm)],'Inventory Movement'!E5,Table4[Movement Type],"In") -> 40 | I5: =SUMIFS(Table4[Quantity],Table4[Wood Type],'Inventory Movement'!A5,Table4[Product Form],'Inventory Movement'!B5,Table4[Width (cm)],'Inventory Movement'!C5,Table4[Thickness (cm)],'Inventory Movement'!D5,Table4[Length (cm)],'Inventory Movement'!E5,Table4[Movement Type],"Out") -> 0 | J5: =SUMIFS(Table5[Quantity],Table5[Wood Type],Table2[[#This Row],[Wood Type]],Table5[Product Form],Table2[[#This Row],[Product Form]],Table5[Width (cm)],Table2[[#This Row],[Width (cm)]],Table5[Thickness (cm)],Table2[[#This Row],[Thickness (cm)]],Table5[Length (cm)],Table2[[#This Row],[Length (cm)]],Table5[Date],">"&DATE(2026,6,5)) -> 133 | K5: =(Table2[[#This Row],[Opening Stock]]+Table2[[#This Row],[Internal Cutting]]+Table2[[#This Row],[Purchases]])-(Table2[[#This Row],[Sales]]+Table2[[#This Row],[External Cutting]]) -> 31 | L5: =(C5/100)*(D5/100)*(E5/100)*Table2[[#This Row],[Current Stock]] -> 0.2325
A6: Shalboard | B6: Boards | C6: 10 | D6: 2.5 | E6: 330 | F6: 732 | G6: =SUMIFS(Table1[Quantity],Table1[Wood Type],Table2[[#This Row],[Wood Type]],Table1[Category],Table2[[#This Row],[Product Form]],Table1[Width (cm)],Table2[[#This Row],[Width (cm)]],Table1[Thickness (cm)],Table2[[#This Row],[Thickness (cm)]],Table1[Length (cm)],Table2[[#This Row],[Length (cm)]]) -> 828 | H6: =SUMIFS(Table4[Quantity],Table4[Wood Type],'Inventory Movement'!A6,Table4[Product Form],'Inventory Movement'!B6,Table4[Width (cm)],'Inventory Movement'!C6,Table4[Thickness (cm)],'Inventory Movement'!D6,Table4[Length (cm)],'Inventory Movement'!E6,Table4[Movement Type],"In") -> 0 | I6: =SUMIFS(Table4[Quantity],Table4[Wood Type],'Inventory Movement'!A6,Table4[Product Form],'Inventory Movement'!B6,Table4[Width (cm)],'Inventory Movement'!C6,Table4[Thickness (cm)],'Inventory Movement'!D6,Table4[Length (cm)],'Inventory Movement'!E6,Table4[Movement Type],"Out") -> 0 | J6: =SUMIFS(Table5[Quantity],Table5[Wood Type],Table2[[#This Row],[Wood Type]],Table5[Product Form],Table2[[#This Row],[Product Form]],Table5[Width (cm)],Table2[[#This Row],[Width (cm)]],Table5[Thickness (cm)],Table2[[#This Row],[Thickness (cm)]],Table5[Length (cm)],Table2[[#This Row],[Length (cm)]],Table5[Date],">"&DATE(2026,6,5)) -> 202 | K6: =(Table2[[#This Row],[Opening Stock]]+Table2[[#This Row],[Internal Cutting]]+Table2[[#This Row],[Purchases]])-(Table2[[#This Row],[Sales]]+Table2[[#This Row],[External Cutting]]) -> 106 | L6: =(C6/100)*(D6/100)*(E6/100)*Table2[[#This Row],[Current Stock]] -> 0.8745
A7: Shalboard | B7: Boards | C7: 10 | D7: 2.5 | E7: 360 | F7: 468 | G7: =SUMIFS(Table1[Quantity],Table1[Wood Type],Table2[[#This Row],[Wood Type]],Table1[Category],Table2[[#This Row],[Product Form]],Table1[Width (cm)],Table2[[#This Row],[Width (cm)]],Table1[Thickness (cm)],Table2[[#This Row],[Thickness (cm)]],Table1[Length (cm)],Table2[[#This Row],[Length (cm)]]) -> 634 | H7: =SUMIFS(Table4[Quantity],Table4[Wood Type],'Inventory Movement'!A7,Table4[Product Form],'Inventory Movement'!B7,Table4[Width (cm)],'Inventory Movement'!C7,Table4[Thickness (cm)],'Inventory Movement'!D7,Table4[Length (cm)],'Inventory Movement'!E7,Table4[Movement Type],"In") -> 0 | I7: =SUMIFS(Table4[Quantity],Table4[Wood Type],'Inventory Movement'!A7,Table4[Product Form],'Inventory Movement'!B7,Table4[Width (cm)],'Inventory Movement'!C7,Table4[Thickness (cm)],'Inventory Movement'!D7,Table4[Length (cm)],'Inventory Movement'!E7,Table4[Movement Type],"Out") -> 0 | J7: =SUMIFS(Table5[Quantity],Table5[Wood Type],Table2[[#This Row],[Wood Type]],Table5[Product Form],Table2[[#This Row],[Product Form]],Table5[Width (cm)],Table2[[#This Row],[Width (cm)]],Table5[Thickness (cm)],Table2[[#This Row],[Thickness (cm)]],Table5[Length (cm)],Table2[[#This Row],[Length (cm)]],Table5[Date],">"&DATE(2026,6,5)) -> 963 | K7: =(Table2[[#This Row],[Opening Stock]]+Table2[[#This Row],[Internal Cutting]]+Table2[[#This Row],[Purchases]])-(Table2[[#This Row],[Sales]]+Table2[[#This Row],[External Cutting]]) -> 797 | L7: =(C7/100)*(D7/100)*(E7/100)*Table2[[#This Row],[Current Stock]] -> 7.173
A8: Shalboard | B8: Boards | C8: 10 | D8: 2.5 | E8: 390 | F8: 342 | G8: =SUMIFS(Table1[Quantity],Table1[Wood Type],Table2[[#This Row],[Wood Type]],Table1[Category],Table2[[#This Row],[Product Form]],Table1[Width (cm)],Table2[[#This Row],[Width (cm)]],Table1[Thickness (cm)],Table2[[#This Row],[Thickness (cm)]],Table1[Length (cm)],Table2[[#This Row],[Length (cm)]]) -> 438 | H8: =SUMIFS(Table4[Quantity],Table4[Wood Type],'Inventory Movement'!A8,Table4[Product Form],'Inventory Movement'!B8,Table4[Width (cm)],'Inventory Movement'!C8,Table4[Thickness (cm)],'Inventory Movement'!D8,Table4[Length (cm)],'Inventory Movement'!E8,Table4[Movement Type],"In") -> 0 | I8: =SUMIFS(Table4[Quantity],Table4[Wood Type],'Inventory Movement'!A8,Table4[Product Form],'Inventory Movement'!B8,Table4[Width (cm)],'Inventory Movement'!C8,Table4[Thickness (cm)],'Inventory Movement'!D8,Table4[Length (cm)],'Inventory Movement'!E8,Table4[Movement Type],"Out") -> 0 | J8: =SUMIFS(Table5[Quantity],Table5[Wood Type],Table2[[#This Row],[Wood Type]],Table5[Product Form],Table2[[#This Row],[Product Form]],Table5[Width (cm)],Table2[[#This Row],[Width (cm)]],Table5[Thickness (cm)],Table2[[#This Row],[Thickness (cm)]],Table5[Length (cm)],Table2[[#This Row],[Length (cm)]],Table5[Date],">"&DATE(2026,6,5)) -> 707 | K8: =(Table2[[#This Row],[Opening Stock]]+Table2[[#This Row],[Internal Cutting]]+Table2[[#This Row],[Purchases]])-(Table2[[#This Row],[Sales]]+Table2[[#This Row],[External Cutting]]) -> 611 | L8: =(C8/100)*(D8/100)*(E8/100)*Table2[[#This Row],[Current Stock]] -> 5.95725
A9: Shalboard | B9: Boards | C9: 10 | D9: 2.5 | E9: 420 | F9: 807 | G9: =SUMIFS(Table1[Quantity],Table1[Wood Type],Table2[[#This Row],[Wood Type]],Table1[Category],Table2[[#This Row],[Product Form]],Table1[Width (cm)],Table2[[#This Row],[Width (cm)]],Table1[Thickness (cm)],Table2[[#This Row],[Thickness (cm)]],Table1[Length (cm)],Table2[[#This Row],[Length (cm)]]) -> 548 | H9: =SUMIFS(Table4[Quantity],Table4[Wood Type],'Inventory Movement'!A9,Table4[Product Form],'Inventory Movement'!B9,Table4[Width (cm)],'Inventory Movement'!C9,Table4[Thickness (cm)],'Inventory Movement'!D9,Table4[Length (cm)],'Inventory Movement'!E9,Table4[Movement Type],"In") -> 0 | I9: =SUMIFS(Table4[Quantity],Table4[Wood Type],'Inventory Movement'!A9,Table4[Product Form],'Inventory Movement'!B9,Table4[Width (cm)],'Inventory Movement'!C9,Table4[Thickness (cm)],'Inventory Movement'!D9,Table4[Length (cm)],'Inventory Movement'!E9,Table4[Movement Type],"Out") -> 5 | J9: =SUMIFS(Table5[Quantity],Table5[Wood Type],Table2[[#This Row],[Wood Type]],Table5[Product Form],Table2[[#This Row],[Product Form]],Table5[Width (cm)],Table2[[#This Row],[Width (cm)]],Table5[Thickness (cm)],Table2[[#This Row],[Thickness (cm)]],Table5[Length (cm)],Table2[[#This Row],[Length (cm)]],Table5[Date],">"&DATE(2026,6,5)) -> 733 | K9: =(Table2[[#This Row],[Opening Stock]]+Table2[[#This Row],[Internal Cutting]]+Table2[[#This Row],[Purchases]])-(Table2[[#This Row],[Sales]]+Table2[[#This Row],[External Cutting]]) -> 987 | L9: =(C9/100)*(D9/100)*(E9/100)*Table2[[#This Row],[Current Stock]] -> 10.3635
A10: Shalboard | B10: Boards | C10: 10 | D10: 2.5 | E10: 450 | F10: 372 | G10: =SUMIFS(Table1[Quantity],Table1[Wood Type],Table2[[#This Row],[Wood Type]],Table1[Category],Table2[[#This Row],[Product Form]],Table1[Width (cm)],Table2[[#This Row],[Width (cm)]],Table1[Thickness (cm)],Table2[[#This Row],[Thickness (cm)]],Table1[Length (cm)],Table2[[#This Row],[Length (cm)]]) -> 366 | H10: =SUMIFS(Table4[Quantity],Table4[Wood Type],'Inventory Movement'!A10,Table4[Product Form],'Inventory Movement'!B10,Table4[Width (cm)],'Inventory Movement'!C10,Table4[Thickness (cm)],'Inventory Movement'!D10,Table4[Length (cm)],'Inventory Movement'!E10,Table4[Movement Type],"In") -> 0 | I10: =SUMIFS(Table4[Quantity],Table4[Wood Type],'Inventory Movement'!A10,Table4[Product Form],'Inventory Movement'!B10,Table4[Width (cm)],'Inventory Movement'!C10,Table4[Thickness (cm)],'Inventory Movement'!D10,Table4[Length (cm)],'Inventory Movement'!E10,Table4[Movement Type],"Out") -> 0 | J10: =SUMIFS(Table5[Quantity],Table5[Wood Type],Table2[[#This Row],[Wood Type]],Table5[Product Form],Table2[[#This Row],[Product Form]],Table5[Width (cm)],Table2[[#This Row],[Width (cm)]],Table5[Thickness (cm)],Table2[[#This Row],[Thickness (cm)]],Table5[Length (cm)],Table2[[#This Row],[Length (cm)]],Table5[Date],">"&DATE(2026,6,5)) -> 719 | K10: =(Table2[[#This Row],[Opening Stock]]+Table2[[#This Row],[Internal Cutting]]+Table2[[#This Row],[Purchases]])-(Table2[[#This Row],[Sales]]+Table2[[#This Row],[External Cutting]]) -> 725 | L10: =(C10/100)*(D10/100)*(E10/100)*Table2[[#This Row],[Current Stock]] -> 8.15625
A11: Shalboard | B11: Boards | C11: 10 | D11: 2.5 | E11: 480 | F11: 891 | G11: =SUMIFS(Table1[Quantity],Table1[Wood Type],Table2[[#This Row],[Wood Type]],Table1[Category],Table2[[#This Row],[Product Form]],Table1[Width (cm)],Table2[[#This Row],[Width (cm)]],Table1[Thickness (cm)],Table2[[#This Row],[Thickness (cm)]],Table1[Length (cm)],Table2[[#This Row],[Length (cm)]]) -> 212 | H11: =SUMIFS(Table4[Quantity],Table4[Wood Type],'Inventory Movement'!A11,Table4[Product Form],'Inventory Movement'!B11,Table4[Width (cm)],'Inventory Movement'!C11,Table4[Thickness (cm)],'Inventory Movement'!D11,Table4[Length (cm)],'Inventory Movement'!E11,Table4[Movement Type],"In") -> 0 | I11: =SUMIFS(Table4[Quantity],Table4[Wood Type],'Inventory Movement'!A11,Table4[Product Form],'Inventory Movement'!B11,Table4[Width (cm)],'Inventory Movement'!C11,Table4[Thickness (cm)],'Inventory Movement'!D11,Table4[Length (cm)],'Inventory Movement'!E11,Table4[Movement Type],"Out") -> 46 | J11: =SUMIFS(Table5[Quantity],Table5[Wood Type],Table2[[#This Row],[Wood Type]],Table5[Product Form],Table2[[#This Row],[Product Form]],Table5[Width (cm)],Table2[[#This Row],[Width (cm)]],Table5[Thickness (cm)],Table2[[#This Row],[Thickness (cm)]],Table5[Length (cm)],Table2[[#This Row],[Length (cm)]],Table5[Date],">"&DATE(2026,6,5)) -> 349 | K11: =(Table2[[#This Row],[Opening Stock]]+Table2[[#This Row],[Internal Cutting]]+Table2[[#This Row],[Purchases]])-(Table2[[#This Row],[Sales]]+Table2[[#This Row],[External Cutting]]) -> 982 | L11: =(C11/100)*(D11/100)*(E11/100)*Table2[[#This Row],[Current Stock]] -> 11.784
A12: Shalboard | B12: Boards | C12: 10 | D12: 2.5 | E12: 510 | F12: 243 | G12: =SUMIFS(Table1[Quantity],Table1[Wood Type],Table2[[#This Row],[Wood Type]],Table1[Category],Table2[[#This Row],[Product Form]],Table1[Width (cm)],Table2[[#This Row],[Width (cm)]],Table1[Thickness (cm)],Table2[[#This Row],[Thickness (cm)]],Table1[Length (cm)],Table2[[#This Row],[Length (cm)]]) -> 191 | H12: =SUMIFS(Table4[Quantity],Table4[Wood Type],'Inventory Movement'!A12,Table4[Product Form],'Inventory Movement'!B12,Table4[Width (cm)],'Inventory Movement'!C12,Table4[Thickness (cm)],'Inventory Movement'!D12,Table4[Length (cm)],'Inventory Movement'!E12,Table4[Movement Type],"In") -> 0 | I12: =SUMIFS(Table4[Quantity],Table4[Wood Type],'Inventory Movement'!A12,Table4[Product Form],'Inventory Movement'!B12,Table4[Width (cm)],'Inventory Movement'!C12,Table4[Thickness (cm)],'Inventory Movement'!D12,Table4[Length (cm)],'Inventory Movement'!E12,Table4[Movement Type],"Out") -> 0 | J12: =SUMIFS(Table5[Quantity],Table5[Wood Type],Table2[[#This Row],[Wood Type]],Table5[Product Form],Table2[[#This Row],[Product Form]],Table5[Width (cm)],Table2[[#This Row],[Width (cm)]],Table5[Thickness (cm)],Table2[[#This Row],[Thickness (cm)]],Table5[Length (cm)],Table2[[#This Row],[Length (cm)]],Table5[Date],">"&DATE(2026,6,5)) -> 571 | K12: =(Table2[[#This Row],[Opening Stock]]+Table2[[#This Row],[Internal Cutting]]+Table2[[#This Row],[Purchases]])-(Table2[[#This Row],[Sales]]+Table2[[#This Row],[External Cutting]]) -> 623 | L12: =(C12/100)*(D12/100)*(E12/100)*Table2[[#This Row],[Current Stock]] -> 7.94325
A13: Shalboard | B13: Boards | C13: 10 | D13: 2.5 | E13: 540 | F13: 0 | G13: =SUMIFS(Table1[Quantity],Table1[Wood Type],Table2[[#This Row],[Wood Type]],Table1[Category],Table2[[#This Row],[Product Form]],Table1[Width (cm)],Table2[[#This Row],[Width (cm)]],Table1[Thickness (cm)],Table2[[#This Row],[Thickness (cm)]],Table1[Length (cm)],Table2[[#This Row],[Length (cm)]]) -> 261 | H13: =SUMIFS(Table4[Quantity],Table4[Wood Type],'Inventory Movement'!A13,Table4[Product Form],'Inventory Movement'!B13,Table4[Width (cm)],'Inventory Movement'!C13,Table4[Thickness (cm)],'Inventory Movement'!D13,Table4[Length (cm)],'Inventory Movement'!E13,Table4[Movement Type],"In") -> 0 | I13: =SUMIFS(Table4[Quantity],Table4[Wood Type],'Inventory Movement'!A13,Table4[Product Form],'Inventory Movement'!B13,Table4[Width (cm)],'Inventory Movement'!C13,Table4[Thickness (cm)],'Inventory Movement'!D13,Table4[Length (cm)],'Inventory Movement'!E13,Table4[Movement Type],"Out") -> 89 | J13: =SUMIFS(Table5[Quantity],Table5[Wood Type],Table2[[#This Row],[Wood Type]],Table5[Product Form],Table2[[#This Row],[Product Form]],Table5[Width (cm)],Table2[[#This Row],[Width (cm)]],Table5[Thickness (cm)],Table2[[#This Row],[Thickness (cm)]],Table5[Length (cm)],Table2[[#This Row],[Length (cm)]],Table5[Date],">"&DATE(2026,6,5)) -> 623 | K13: =(Table2[[#This Row],[Opening Stock]]+Table2[[#This Row],[Internal Cutting]]+Table2[[#This Row],[Purchases]])-(Table2[[#This Row],[Sales]]+Table2[[#This Row],[External Cutting]]) -> 273 | L13: =(C13/100)*(D13/100)*(E13/100)*Table2[[#This Row],[Current Stock]] -> 3.6855
... A45: Shalboard | B45: Boards | C45: 10 | D45: 2.5 | E45: 600 | F45: 60 | G45: =SUMIFS(Table1[Quantity],Table1[Wood Type],Table2[[#This Row],[Wood Type]],Table1[Category],Table2[[#This Row],[Product Form]],Table1[Width (cm)],Table2[[#This Row],[Width (cm)]],Table1[Thickness (cm)],Table2[[#This Row],[Thickness (cm)]],Table1[Length (cm)],Table2[[#This Row],[Length (cm)]]) -> 0 | H45: =SUMIFS(Table4[Quantity],Table4[Wood Type],'Inventory Movement'!A45,Table4[Product Form],'Inventory Movement'!B45,Table4[Width (cm)],'Inventory Movement'!C45,Table4[Thickness (cm)],'Inventory Movement'!D45,Table4[Length (cm)],'Inventory Movement'!E45,Table4[Movement Type],"In") -> 0 | I45: =SUMIFS(Table4[Quantity],Table4[Wood Type],'Inventory Movement'!A45,Table4[Product Form],'Inventory Movement'!B45,Table4[Width (cm)],'Inventory Movement'!C45,Table4[Thickness (cm)],'Inventory Movement'!D45,Table4[Length (cm)],'Inventory Movement'!E45,Table4[Movement Type],"Out") -> 0 | J45: =SUMIFS(Table5[Quantity],Table5[Wood Type],Table2[[#This Row],[Wood Type]],Table5[Product Form],Table2[[#This Row],[Product Form]],Table5[Width (cm)],Table2[[#This Row],[Width (cm)]],Table5[Thickness (cm)],Table2[[#This Row],[Thickness (cm)]],Table5[Length (cm)],Table2[[#This Row],[Length (cm)]],Table5[Date],">"&DATE(2026,6,5)) -> 0 | K45: =(Table2[[#This Row],[Opening Stock]]+Table2[[#This Row],[Internal Cutting]]+Table2[[#This Row],[Purchases]])-(Table2[[#This Row],[Sales]]+Table2[[#This Row],[External Cutting]]) -> 60 | L45: =(C45/100)*(D45/100)*(E45/100)*Table2[[#This Row],[Current Stock]] -> 0.9

Sheet Collections 
A1: Date | B1: Customer Name | C1: Customer ID | D1: Collected Amount | E1: Transaction Type
A2: 46175 | B2: yasser | C2: =_xlfn.XLOOKUP(B2,'Customer Receivables'!A:A,'Customer Receivables'!B:B," ") -> C-007 | D2: 10000 | E2: Credit Collection
A3: 46177 | B3: mohamed ghazy | C3: =_xlfn.XLOOKUP(B3,'Customer Receivables'!A:A,'Customer Receivables'!B:B," ") -> C-027 | D3: 5000 | E3: Credit Collection
A4: 46177 | B4: ahmed antar | C4: =_xlfn.XLOOKUP(B4,'Customer Receivables'!A:A,'Customer Receivables'!B:B," ") -> C-031 | D4: 10000 | E4: Credit Collection
A5: 46177 | B5: eng mohamed mostafa | C5: =_xlfn.XLOOKUP(B5,'Customer Receivables'!A:A,'Customer Receivables'!B:B," ") -> C-034 | D5: 5000 | E5: Credit Collection
A6: 46177 | B6: ashraf mhalet marhoum | C6: =_xlfn.XLOOKUP(B6,'Customer Receivables'!A:A,'Customer Receivables'!B:B," ") -> C-029 | D6: 5000 | E6: Credit Collection
A7: 46177 | B7: samir elshater | C7: =_xlfn.XLOOKUP(B7,'Customer Receivables'!A:A,'Customer Receivables'!B:B," ") -> C-032 | D7: 9000 | E7: Credit Collection
A8: 46177 | B8: elsayed abdallah | C8: =_xlfn.XLOOKUP(B8,'Customer Receivables'!A:A,'Customer Receivables'!B:B," ") -> C-004 | D8: 15000 | E8: Credit Collection
A9: 46177 | B9: yasser | C9: =_xlfn.XLOOKUP(B9,'Customer Receivables'!A:A,'Customer Receivables'!B:B," ") -> C-007 | D9: 10000 | E9: Credit Collection
A10: 46177 | B10: yasser | C10: =_xlfn.XLOOKUP(B10,'Customer Receivables'!A:A,'Customer Receivables'!B:B," ") -> C-007 | D10: 40200 | E10: Credit Collection
A11: 46180 | B11: yasser | C11: =_xlfn.XLOOKUP(B11,'Customer Receivables'!A:A,'Customer Receivables'!B:B," ") -> C-007 | D11: 10000 | E11: Credit Collection
A12: 46182 | B12: yasser | C12: =_xlfn.XLOOKUP(B12,'Customer Receivables'!A:A,'Customer Receivables'!B:B," ") -> C-007 | D12: 10000 | E12: Credit Collection
A13: 46182 | B13: elsayed madyan | C13: =_xlfn.XLOOKUP(B13,'Customer Receivables'!A:A,'Customer Receivables'!B:B," ") -> C-006 | D13: 2350 | E13: Credit Collection
... A136: 46234 | B136: yasser | C136: =_xlfn.XLOOKUP(B136,'Customer Receivables'!A:A,'Customer Receivables'!B:B," ") -> C-007 | D136: 20000 | E136: Credit Collection

Sheet Accounts (Cash Accounts)
A1: Opening Balance | B1: Collections | C1: Supplier Payments | D1: Expenses | E1: Current Balance
A2: 276485 | B2: =SUM(Table3[Collected Amount]) -> 1383005 | C2: =SUM(Table6[Payment Amount]) -> 1470095.6 | D2: =SUM(Table10[Amount]) -> 57955 | E2: =Table410[[#This Row],[Opening Balance]]+Table410[[#This Row],[Collections]]-Table410[[#This Row],[Supplier Payments]]-Table410[[#This Row],[Expenses]] -> 131439.4

Sheet Expenses
A1: Date | B1: Amount | C1: Description | D1: Expense Category
A2: 46175 | B2: 50 | C2: Breakfast | D2: Labor Expenses
A3: 46175 | B3: 190 | C3: Electricity Bill | D3: Facility Expenses
A4: 46177 | B4: 100 | C4: Breakfast | D4: Labor Expenses
A5: 46177 | B5: 500 | C5: sayed zalat | D5: Owner Withdrawal
A6: 46178 | B6: 100 | C6: tea | D6: Facility Expenses
A7: 46178 | B7: 50 | C7: sugar | D7: Labor Expenses
A8: 46179 | B8: 100 | C8: Breakfast | D8: Labor Expenses
A9: 46179 | B9: 2000 | C9: mohamed zalat | D9: Salary
A10: 46180 | B10: 100 | C10: Statement | D10: Wood Cost
A11: 46180 | B11: 50 | C11: sayed zalat | D11: Owner Withdrawal
A12: 46193 | B12: 1000 | C12: mohamed zalat | D12: Salary
A13: 46193 | B13: 3000 | C13: khaled khadr | D13: Salary
... A72: 46233 | B72: 50 | C72: vodafone cash | D72: Customer Expenses

Sheet Customer Receivables
A1: Customer Name | B1: Customer ID | C1: Total Sales | D1: Opening Balance | E1: Total Payments | F1: Outstanding Balance
A2: taha sharaf | B2: C-001 | C2: =SUMIF(Table1[Customer ID],'Customer Receivables'!B2,Table1[Agreed Amount]) -> 46800 | D2: =SUMIF('Opening Receivables'!C:C,'Customer Receivables'!B2,'Opening Receivables'!D:D) -> 0 | E2: =SUMIF(Table3[Customer ID],'Customer Receivables'!B2,Table3[Collected Amount]) -> 46800 | F2: =C2+D2-E2 -> 0
A3: elsayed badawy | B3: C-002 | C3: =SUMIF(Table1[Customer ID],'Customer Receivables'!B3,Table1[Agreed Amount]) -> 140110 | D3: =SUMIF('Opening Receivables'!C:C,'Customer Receivables'!B3,'Opening Receivables'!D:D) -> -57400 | E3: =SUMIF(Table3[Customer ID],'Customer Receivables'!B3,Table3[Collected Amount]) -> 40000 | F3: =C3+D3-E3 -> 42710
A4: samy zalat | B4: C-003 | C4: =SUMIF(Table1[Customer ID],'Customer Receivables'!B4,Table1[Agreed Amount]) -> 332440 | D4: =SUMIF('Opening Receivables'!C:C,'Customer Receivables'!B4,'Opening Receivables'!D:D) -> 42560 | E4: =SUMIF(Table3[Customer ID],'Customer Receivables'!B4,Table3[Collected Amount]) -> 156000 | F4: =C4+D4-E4 -> 219000
A5: elsayed abdallah | B5: C-004 | C5: =SUMIF(Table1[Customer ID],'Customer Receivables'!B5,Table1[Agreed Amount]) -> 19785 | D5: =SUMIF('Opening Receivables'!C:C,'Customer Receivables'!B5,'Opening Receivables'!D:D) -> 0 | E5: =SUMIF(Table3[Customer ID],'Customer Receivables'!B5,Table3[Collected Amount]) -> 19785 | F5: =C5+D5-E5 -> 0
A6: elsayed madyan | B6: C-006 | C6: =SUMIF(Table1[Customer ID],'Customer Receivables'!B6,Table1[Agreed Amount]) -> 56650 | D6: =SUMIF('Opening Receivables'!C:C,'Customer Receivables'!B6,'Opening Receivables'!D:D) -> 2350 | E6: =SUMIF(Table3[Customer ID],'Customer Receivables'!B6,Table3[Collected Amount]) -> 50600 | F6: =C6+D6-E6 -> 8400
A7: yasser | B7: C-007 | C7: =SUMIF(Table1[Customer ID],'Customer Receivables'!B7,Table1[Agreed Amount]) -> 185000 | D7: =SUMIF('Opening Receivables'!C:C,'Customer Receivables'!B7,'Opening Receivables'!D:D) -> 49200 | E7: =SUMIF(Table3[Customer ID],'Customer Receivables'!B7,Table3[Collected Amount]) -> 225200 | F7: =C7+D7-E7 -> 9000
A8: ragab elwassal | B8: C-008 | C8: =SUMIF(Table1[Customer ID],'Customer Receivables'!B8,Table1[Agreed Amount]) -> 6670 | D8: =SUMIF('Opening Receivables'!C:C,'Customer Receivables'!B8,'Opening Receivables'!D:D) -> 0 | E8: =SUMIF(Table3[Customer ID],'Customer Receivables'!B8,Table3[Collected Amount]) -> 6670 | F8: =C8+D8-E8 -> 0
A9: tba3 elsayed madyan | B9: C-009 | C9: =SUMIF(Table1[Customer ID],'Customer Receivables'!B9,Table1[Agreed Amount]) -> 8000 | D9: =SUMIF('Opening Receivables'!C:C,'Customer Receivables'!B9,'Opening Receivables'!D:D) -> 0 | E9: =SUMIF(Table3[Customer ID],'Customer Receivables'!B9,Table3[Collected Amount]) -> 8000 | F9: =C9+D9-E9 -> 0
A10: goda elbtanony | B10: C-010 | C10: =SUMIF(Table1[Customer ID],'Customer Receivables'!B10,Table1[Agreed Amount]) -> 21600 | D10: =SUMIF('Opening Receivables'!C:C,'Customer Receivables'!B10,'Opening Receivables'!D:D) -> 0 | E10: =SUMIF(Table3[Customer ID],'Customer Receivables'!B10,Table3[Collected Amount]) -> 21600 | F10: =C10+D10-E10 -> 0
A11: shawky | B11: C-011 | C11: =SUMIF(Table1[Customer ID],'Customer Receivables'!B11,Table1[Agreed Amount]) -> 28820 | D11: =SUMIF('Opening Receivables'!C:C,'Customer Receivables'!B11,'Opening Receivables'!D:D) -> 0 | E11: =SUMIF(Table3[Customer ID],'Customer Receivables'!B11,Table3[Collected Amount]) -> 22465 | F11: =C11+D11-E11 -> 6355
A12: alaa salama | B12: C-012 | C12: =SUMIF(Table1[Customer ID],'Customer Receivables'!B12,Table1[Agreed Amount]) -> 21875 | D12: =SUMIF('Opening Receivables'!C:C,'Customer Receivables'!B12,'Opening Receivables'!D:D) -> 0 | E12: =SUMIF(Table3[Customer ID],'Customer Receivables'!B12,Table3[Collected Amount]) -> 21275 | F12: =C12+D12-E12 -> 600
A13: alam shahen | B13: C-013 | C13: =SUMIF(Table1[Customer ID],'Customer Receivables'!B13,Table1[Agreed Amount]) -> 41600 | D13: =SUMIF('Opening Receivables'!C:C,'Customer Receivables'!B13,'Opening Receivables'!D:D) -> 0 | E13: =SUMIF(Table3[Customer ID],'Customer Receivables'!B13,Table3[Collected Amount]) -> 41600 | F13: =C13+D13-E13 -> 0
... A57: salah eltawel | B57: C-058 | C57: =SUMIF(Table1[Customer ID],'Customer Receivables'!B57,Table1[Agreed Amount]) -> 31400 | D57: =SUMIF('Opening Receivables'!C:C,'Customer Receivables'!B57,'Opening Receivables'!D:D) -> 0 | E57: =SUMIF(Table3[Customer ID],'Customer Receivables'!B57,Table3[Collected Amount]) -> 31400 | F57: =C57+D57-E57 -> 0
C58: =SUMIF(Table1[Customer ID],'Customer Receivables'!B58,Table1[Agreed Amount]) -> 0 | D58: =SUMIF('Opening Receivables'!C:C,'Customer Receivables'!B58,'Opening Receivables'!D:D) -> 0 | E58: =SUMIF(Table3[Customer ID],'Customer Receivables'!B58,Table3[Collected Amount]) -> 0 | F58: =C58+D58-E58 -> 0
C59: =SUMIF(Table1[Customer ID],'Customer Receivables'!B59,Table1[Agreed Amount]) -> 0 | D59: =SUMIF('Opening Receivables'!C:C,'Customer Receivables'!B59,'Opening Receivables'!D:D) -> 0 | E59: =SUMIF(Table3[Customer ID],'Customer Receivables'!B59,Table3[Collected Amount]) -> 0 | F59: =C59+D59-E59 -> 0
C60: =SUMIF(Table1[Customer ID],'Customer Receivables'!B60,Table1[Agreed Amount]) -> 0 | D60: =SUMIF('Opening Receivables'!C:C,'Customer Receivables'!B60,'Opening Receivables'!D:D) -> 0 | E60: =SUMIF(Table3[Customer ID],'Customer Receivables'!B60,Table3[Collected Amount]) -> 0 | F60: =C60+D60-E60 -> 0
C61: =SUMIF(Table1[Customer ID],'Customer Receivables'!B61,Table1[Agreed Amount]) -> 0 | D61: =SUMIF('Opening Receivables'!C:C,'Customer Receivables'!B61,'Opening Receivables'!D:D) -> 0 | E61: =SUMIF(Table3[Customer ID],'Customer Receivables'!B61,Table3[Collected Amount]) -> 0 | F61: =C61+D61-E61 -> 0
C62: =SUMIF(Table1[Customer ID],'Customer Receivables'!B62,Table1[Agreed Amount]) -> 0 | D62: =SUMIF('Opening Receivables'!C:C,'Customer Receivables'!B62,'Opening Receivables'!D:D) -> 0 | E62: =SUMIF(Table3[Customer ID],'Customer Receivables'!B62,Table3[Collected Amount]) -> 0 | F62: =C62+D62-E62 -> 0

Sheet Wood Cutting
A1: Operation ID | B1: Date | C1: Wood Type | D1: Product Form | E1: Width (cm) | F1: Thickness (cm) | G1: Length (cm) | H1: Movement Type | I1: Quantity
A2: 1001 | B2: 46202 | C2: Shalboard | D2: Boards | E2: 10 | F2: 2.5 | G2: 480 | H2: Out | I2: 40
A3: 1001 | B3: 46202 | C3: Shalboard | D3: Boards | E3: 10 | F3: 2.5 | G3: 300 | H3: In | I3: 40
A4: 1001 | B4: 46202 | C4: Shalboard | D4: Battens | E4: 10 | F4: 2.5 | G4: 180 | H4: In | I4: 40
A5: 1002 | B5: 46209 | C5: Shalboard | D5: Boards | E5: 12.5 | F5: 2.5 | G5: 510 | H5: Out | I5: 71
A6: 1002 | B6: 46209 | C6: Shalboard | D6: Boards | E6: 12.5 | F6: 2.5 | G6: 240 | H6: In | I6: 71
A7: 1002 | B7: 46209 | C7: Shalboard | D7: Boards | E7: 12.5 | F7: 2.5 | G7: 270 | H7: In | I7: 72
A8: 1003 | B8: 46209 | C8: Shalboard | D8: Boards | E8: 12.5 | F8: 2.5 | G8: 480 | H8: Out | I8: 1
A9: 1003 | B9: 46209 | C9: Shalboard | D9: Boards | E9: 12.5 | F9: 2.5 | G9: 270 | H9: In | I9: 1
A10: 1003 | B10: 46209 | C10: Shalboard | D10: Boards | E10: 12.5 | F10: 2.5 | G10: 210 | H10: In | I10: 1
A11: 1004 | B11: 46211 | C11: Shalboard | D11: Boards | E11: 10 | F11: 2.5 | G11: 480 | H11: Out | I11: 6
A12: 1004 | B12: 46211 | C12: Shalboard | D12: Boards | E12: 10 | F12: 2.5 | G12: 240 | H12: In | I12: 12
A13: 1005 | B13: 46211 | C13: Shalboard | D13: Boards | E13: 10 | F13: 2.5 | G13: 420 | H13: Out | I13: 5
... A20: 1008 | B20: 46234 | C20: Shalboard | D20: Boards | E20: 10 | F20: 2.5 | G20: 270 | H20: In | I20: 86

Sheet Supplier Payments
A1: Date | B1: Supplier ID | C1: Payment Amount | D1: Payment Method | E1: Notes
A2: 46165 | B2: SUP-001 | C2: 256960 | D2: Cash
A3: 46177 | B3: SUP-002 | C3: 196635.6 | D3: Cash
A4: 46183 | B4: SUP-001 | C4: 105000 | D4: Bank Transfer
A5: 46189 | B5: SUP-001 | C5: 120000 | D5: Bank Transfer
A6: 46197 | B6: SUP-001 | C6: 105000 | D6: Bank Transfer
A7: 46204 | B7: SUP-001 | C7: 125000 | D7: Bank Transfer
A8: 46211 | B8: SUP-001 | C8: 200000 | D8: Cash
A9: 46218 | B9: SUP-001 | C9: 120000 | D9: Bank Transfer
A10: 46225 | B10: SUP-001 | C10: 75000 | D10: Bank Transfer
A11: 46224 | B11: SUP-003 | C11: 1500 | D11: Cash
A12: 46230 | B12: SUP-001 | C12: 65000 | D12: Bank Transfer
A13: 46233 | B13: SUP-001 | C13: 100000 | D13: Bank Transfer

Sheet Suppliers
A1: Supplier ID | B1: Supplier Name | C1: Opening Balance | D1: Total Purchases | E1: Total Payments | F1: Outstanding Balance
A2: SUP-001 | B2: Gamal | C2: 451560 | D2: =SUMIFS(Table511[Total Amount],Table511[Supplier ID],Table8[[#This Row],[Supplier ID]]) -> 1727667.6 | E2: =SUMIFS(Table6[Payment Amount],Table6[Supplier ID],Table8[[#This Row],[Supplier ID]]) -> 1271960 | F2: =C2+D2-E2 -> 907267.61
A3: SUP-002 | C3: 0 | D3: =SUMIFS(Table511[Total Amount],Table511[Supplier ID],Table8[[#This Row],[Supplier ID]]) -> 196635.6 | E3: =SUMIFS(Table6[Payment Amount],Table6[Supplier ID],Table8[[#This Row],[Supplier ID]]) -> 196635.6 | F3: =C3+D3-E3 -> 0

Sheet Purchase Summary
A1: Supplier Invoice No. | B1: Date | C1: Supplier Name | D1: Supplier ID | E1: Wood Type | F1: Product Form | G1: Width (cm) | H1: Thickness (cm) | I1: Volume (m³) | J1: Price per Cubic Meter | K1: Total Amount
A2: AC-001 | B2: 46165 | C2: Gamal | D2: SUP-001 | E2: Shalboard | F2: Boards | G2: 10 | H2: 2.5 | I2: 35.73525 | J2: 19125 | K2: =Table511[[#This Row],[Volume (m³)]]*Table511[[#This Row],[Price per Cubic Meter]] -> 683436.66
A3: AC-001 | B3: 46165 | C3: Gamal | D3: SUP-001 | E3: New Timber | F3: Beams | G3: 7.5 | H3: 7.5 | I3: 3.054375 | J3: 20925 | K3: =Table511[[#This Row],[Volume (m³)]]*Table511[[#This Row],[Price per Cubic Meter]] -> 63912.797
A4: AC-002 | B4: 46177 | D4: SUP-002 | E4: New Timber | F4: Beams | G4: 9 | H4: 7 | I4: 6.804 | J4: 20400 | K4: =Table511[[#This Row],[Volume (m³)]]*Table511[[#This Row],[Price per Cubic Meter]] -> 138801.6
A5: AC-002 | B5: 46177 | D5: SUP-002 | E5: New Timber | F5: Beams | G5: 7.5 | H5: 7.5 | I5: 2.835 | J5: 20400 | K5: =Table511[[#This Row],[Volume (m³)]]*Table511[[#This Row],[Price per Cubic Meter]] -> 57834
A6: AC-003 | B6: 46211 | C6: Gamal | D6: SUP-001 | E6: Shalboard | F6: Boards | G6: 10 | H6: 2.5 | I6: 34.2379 | J6: 16025 | K6: =Table511[[#This Row],[Volume (m³)]]*Table511[[#This Row],[Price per Cubic Meter]] -> 548662.35
A7: AC-003 | B7: 46211 | C7: Gamal | D7: SUP-001 | E7: Shalboard | F7: Boards | G7: 10 | H7: 2.5 | I7: 26.9364 | J7: 16025 | K7: =Table511[[#This Row],[Volume (m³)]]*Table511[[#This Row],[Price per Cubic Meter]] -> 431655.81
A8: AC-004 | B8: 46224 | C8: Ibrahim Nasr | D8: SUP-003 | E8: Used Timber | F8: Beams | G8: 9 | H8: 7 | I8: 0.126 | J8: 11905 | K8: =Table511[[#This Row],[Volume (m³)]]*Table511[[#This Row],[Price per Cubic Meter]] -> 1500.03

Sheet Purchase Details
A1: Supplier Invoice No. | B1: Date | C1: Supplier Name | D1: Supplier ID | E1: Wood Type | F1: Product Form | G1: Width (cm) | H1: Thickness (cm) | I1: Length (cm) | J1: Quantity | K1: Volume (m³) | L1: Price per Cubic Meter | M1: Average Purchase Price
A2: AC-001 | B2: 46165 | C2: Gamal | D2: SUP-001 | E2: Shalboard | F2: Boards | G2: 10 | H2: 2.5 | I2: 300 | J2: 457 | K2: =(G2/100)*(H2/100)*(I2/100)*J2 -> 3.4275 | L2: 19125 | M2: =AVERAGE(Table5[Price per Cubic Meter]) -> 17243.966
A3: AC-001 | B3: 46165 | C3: Gamal | D3: SUP-001 | E3: Shalboard | F3: Boards | G3: 10 | H3: 2.5 | I3: 330 | J3: 451 | K3: =(G3/100)*(H3/100)*(I3/100)*J3 -> 3.72075 | L3: 19125 | M3: =AVERAGE(Table5[Price per Cubic Meter]) -> 17243.966
A4: AC-001 | B4: 46165 | C4: Gamal | D4: SUP-001 | E4: Shalboard | F4: Boards | G4: 10 | H4: 2.5 | I4: 360 | J4: 459 | K4: =(G4/100)*(H4/100)*(I4/100)*J4 -> 4.131 | L4: 19125 | M4: =AVERAGE(Table5[Price per Cubic Meter]) -> 17243.966
A5: AC-001 | B5: 46165 | C5: Gamal | D5: SUP-001 | E5: Shalboard | F5: Boards | G5: 10 | H5: 2.5 | I5: 390 | J5: 449 | K5: =(G5/100)*(H5/100)*(I5/100)*J5 -> 4.37775 | L5: 19125 | M5: =AVERAGE(Table5[Price per Cubic Meter]) -> 17243.966
A6: AC-001 | B6: 46165 | C6: Gamal | D6: SUP-001 | E6: Shalboard | F6: Boards | G6: 10 | H6: 2.5 | I6: 420 | J6: 901 | K6: =(G6/100)*(H6/100)*(I6/100)*J6 -> 9.4605 | L6: 19125 | M6: =AVERAGE(Table5[Price per Cubic Meter]) -> 17243.966
A7: AC-001 | B7: 46165 | C7: Gamal | D7: SUP-001 | E7: Shalboard | F7: Boards | G7: 10 | H7: 2.5 | I7: 450 | J7: 451 | K7: =(G7/100)*(H7/100)*(I7/100)*J7 -> 5.07375 | L7: 19125 | M7: =AVERAGE(Table5[Price per Cubic Meter]) -> 17243.966
A8: AC-001 | B8: 46165 | C8: Gamal | D8: SUP-001 | E8: Shalboard | F8: Boards | G8: 10 | H8: 2.5 | I8: 480 | J8: 462 | K8: =(G8/100)*(H8/100)*(I8/100)*J8 -> 5.544 | L8: 19125 | M8: =AVERAGE(Table5[Price per Cubic Meter]) -> 17243.966
A9: AC-001 | B9: 46165 | C9: Gamal | D9: SUP-001 | E9: New Timber | F9: Beams | G9: 7.5 | H9: 7.5 | I9: 300 | J9: 181 | K9: =(G9/100)*(H9/100)*(I9/100)*J9 -> 3.054375 | L9: 20925 | M9: =AVERAGE(Table5[Price per Cubic Meter]) -> 17243.966
A10: AC-002 | B10: 46177 | D10: SUP-002 | E10: New Timber | F10: Beams | G10: 9 | H10: 7 | I10: 300 | J10: 360 | K10: =(G10/100)*(H10/100)*(I10/100)*J10 -> 6.804 | L10: 20400 | M10: =AVERAGE(Table5[Price per Cubic Meter]) -> 17243.966
A11: AC-002 | B11: 46177 | D11: SUP-002 | E11: New Timber | F11: Beams | G11: 7.5 | H11: 7.5 | I11: 300 | J11: 168 | K11: =(G11/100)*(H11/100)*(I11/100)*J11 -> 2.835 | L11: 20400 | M11: =AVERAGE(Table5[Price per Cubic Meter]) -> 17243.966
A12: AC-003 | B12: 46211 | C12: Gamal | D12: SUP-001 | E12: Shalboard | F12: Battens | G12: 10 | H12: 2.5 | I12: 90 | J12: 416 | K12: =(G12/100)*(H12/100)*(I12/100)*J12 -> 0.936 | L12: 16025 | M12: =AVERAGE(Table5[Price per Cubic Meter]) -> 17243.966
A13: AC-003 | B13: 46211 | C13: Gamal | D13: SUP-001 | E13: Shalboard | F13: Battens | G13: 10 | H13: 2.5 | I13: 120 | J13: 186 | K13: =(G13/100)*(H13/100)*(I13/100)*J13 -> 0.558 | L13: 16025 | M13: =AVERAGE(Table5[Price per Cubic Meter]) -> 17243.966
A14: AC-003 | B14: 46211 | C14: Gamal | D14: SUP-001 | E14: Shalboard | F14: Battens | G14: 10 | H14: 2.5 | I14: 150 | J14: 87 | K14: =(G14/100)*(H14/100)*(I14/100)*J14 -> 0.32625 | L14: 16025 | M14: =AVERAGE(Table5[Price per Cubic Meter]) -> 17243.966
A15: AC-003 | B15: 46211 | C15: Gamal | D15: SUP-001 | E15: Shalboard | F15: Battens | G15: 10 | H15: 2.5 | I15: 180 | J15: 75 | K15: =(G15/100)*(H15/100)*(I15/100)*J15 -> 0.3375 | L15: 16025 | M15: =AVERAGE(Table5[Price per Cubic Meter]) -> 17243.966
A16: AC-003 | B16: 46211 | C16: Gamal | D16: SUP-001 | E16: Shalboard | F16: Boards | G16: 10 | H16: 2.5 | I16: 210 | J16: 91 | K16: =(G16/100)*(H16/100)*(I16/100)*J16 -> 0.47775 | L16: 16025 | M16: =AVERAGE(Table5[Price per Cubic Meter]) -> 17243.966
A17: AC-003 | B17: 46211 | C17: Gamal | D17: SUP-001 | E17: Shalboard | F17: Boards | G17: 10 | H17: 2.5 | I17: 240 | J17: 313 | K17: =(G17/100)*(H17/100)*(I17/100)*J17 -> 1.878 | L17: 16025 | M17: =AVERAGE(Table5[Price per Cubic Meter]) -> 17243.966
A18: AC-003 | B18: 46211 | C18: Gamal | D18: SUP-001 | E18: Shalboard | F18: Boards | G18: 10 | H18: 2.5 | I18: 270 | J18: 249 | K18: =(G18/100)*(H18/100)*(I18/100)*J18 -> 1.68075 | L18: 16025 | M18: =AVERAGE(Table5[Price per Cubic Meter]) -> 17243.966
A19: AC-003 | B19: 46211 | C19: Gamal | D19: SUP-001 | E19: Shalboard | F19: Boards | G19: 10 | H19: 2.5 | I19: 300 | J19: 133 | K19: =(G19/100)*(H19/100)*(I19/100)*J19 -> 0.9975 | L19: 16025 | M19: =AVERAGE(Table5[Price per Cubic Meter]) -> 17243.966
A20: AC-003 | B20: 46211 | C20: Gamal | D20: SUP-001 | E20: Shalboard | F20: Boards | G20: 10 | H20: 2.5 | I20: 330 | J20: 202 | K20: =(G20/100)*(H20/100)*(I20/100)*J20 -> 1.6665 | L20: 16025 | M20: =AVERAGE(Table5[Price per Cubic Meter]) -> 17243.966
A21: AC-003 | B21: 46211 | C21: Gamal | D21: SUP-001 | E21: Shalboard | F21: Boards | G21: 10 | H21: 2.5 | I21: 360 | J21: 963 | K21: =(G21/100)*(H21/100)*(I21/100)*J21 -> 8.667 | L21: 16025 | M21: =AVERAGE(Table5[Price per Cubic Meter]) -> 17243.966
A22: AC-003 | B22: 46211 | C22: Gamal | D22: SUP-001 | E22: Shalboard | F22: Boards | G22: 10 | H22: 2.5 | I22: 390 | J22: 707 | K22: =(G22/100)*(H22/100)*(I22/100)*J22 -> 6.89325 | L22: 16025 | M22: =AVERAGE(Table5[Price per Cubic Meter]) -> 17243.966
A23: AC-003 | B23: 46211 | C23: Gamal | D23: SUP-001 | E23: Shalboard | F23: Boards | G23: 10 | H23: 2.5 | I23: 420 | J23: 733 | K23: =(G23/100)*(H23/100)*(I23/100)*J23 -> 7.6965 | L23: 16025 | M23: =AVERAGE(Table5[Price per Cubic Meter]) -> 17243.966
... A30: AC-004 | B30: 46224 | C30: Ibrahim Nasr | D30: SUP-003 | E30: Used Timber | F30: Beams | G30: 9 | H30: 7 | I30: 400 | J30: 5 | K30: =(G30/100)*(H30/100)*(I30/100)*J30 -> 0.126 | L30: 16025 | M30: =AVERAGE(Table5[Price per Cubic Meter]) -> 17243.966

Sheet Opening Receivables
A1: Opening Balance Date | B1: Customer Name | C1: Customer ID | D1: Opening Balance | E1: Notes
A2: 46165 | B2: ashraf mhalet marhoum | C2: =_xlfn.XLOOKUP(B2,'Customer Receivables'!A:A,'Customer Receivables'!B:B," ") -> C-029 | D2: 10000
A3: 46133 | B3: alhag araby | C3: =_xlfn.XLOOKUP(B3,'Customer Receivables'!A:A,'Customer Receivables'!B:B," ") -> C-035 | D3: 27800
A4: 46171 | B4: yasser | C4: =_xlfn.XLOOKUP(B4,'Customer Receivables'!A:A,'Customer Receivables'!B:B," ") -> C-007 | D4: 49200
A5: 46168 | B5: mohamed ghazy | C5: =_xlfn.XLOOKUP(B5,'Customer Receivables'!A:A,'Customer Receivables'!B:B," ") -> C-027 | D5: 9000
A6: 46163 | B6: eng mohamed mostafa | C6: =_xlfn.XLOOKUP(B6,'Customer Receivables'!A:A,'Customer Receivables'!B:B," ") -> C-034 | D6: 40000
A7: 46163 | B7: ahmed antar | C7: =_xlfn.XLOOKUP(B7,'Customer Receivables'!A:A,'Customer Receivables'!B:B," ") -> C-031 | D7: 35500
A8: 45797 | B8: elsayed madyan | C8: =_xlfn.XLOOKUP(B8,'Customer Receivables'!A:A,'Customer Receivables'!B:B," ") -> C-006 | D8: 2350
A9: 46168 | B9: mohamed ali | C9: =_xlfn.XLOOKUP(B9,'Customer Receivables'!A:A,'Customer Receivables'!B:B," ") -> C-033 | D9: 16000
A10: 46165 | B10: samy zalat | C10: =_xlfn.XLOOKUP(B10,'Customer Receivables'!A:A,'Customer Receivables'!B:B," ") -> C-003 | D10: 29560
A11: 46167 | B11: elsayed badawy | C11: =_xlfn.XLOOKUP(B11,'Customer Receivables'!A:A,'Customer Receivables'!B:B," ") -> C-002 | D11: 2500
A12: 46165 | B12: samir elshater | C12: =_xlfn.XLOOKUP(B12,'Customer Receivables'!A:A,'Customer Receivables'!B:B," ") -> C-032 | D12: 9000
A13: 46190 | B13: samy zalat | C13: =_xlfn.XLOOKUP(B13,'Customer Receivables'!A:A,'Customer Receivables'!B:B," ") -> C-003 | D13: 2000 | E13: محمد غازي
A14: 46182 | B14: samy zalat | C14: =_xlfn.XLOOKUP(B14,'Customer Receivables'!A:A,'Customer Receivables'!B:B," ") -> C-003 | D14: 11000 | E14: نقدي
A15: 46186 | B15: elsayed badawy | C15: =_xlfn.XLOOKUP(B15,'Customer Receivables'!A:A,'Customer Receivables'!B:B," ") -> C-002 | D15: -8100 | E15: عدد 30 عرق 3 متر
A16: 46188 | B16: elsayed badawy | C16: =_xlfn.XLOOKUP(B16,'Customer Receivables'!A:A,'Customer Receivables'!B:B," ") -> C-002 | D16: -34100 | E16: عدد 155 عرق 270
A17: 46087 | B17: elsayed badawy | C17: =_xlfn.XLOOKUP(B17,'Customer Receivables'!A:A,'Customer Receivables'!B:B," ") -> C-002 | D17: 4050 | E17: عروق علي الشحات
A18: 46201 | B18: elsayed badawy | C18: =_xlfn.XLOOKUP(B18,'Customer Receivables'!A:A,'Customer Receivables'!B:B," ") -> C-002 | D18: -2500 | E18: عدد 10 عروق 3 متر
A19: 46208 | B19: elsayed badawy | C19: =_xlfn.XLOOKUP(B19,'Customer Receivables'!A:A,'Customer Receivables'!B:B," ") -> C-002 | D19: -13200 | E19: عدد 60 عرق 270
A20: 46209 | B20: elsayed badawy | C20: =_xlfn.XLOOKUP(B20,'Customer Receivables'!A:A,'Customer Receivables'!B:B," ") -> C-002 | D20: -4400 | E20: عدد 20 عرق 271
A21: 46209 | B21: elsayed badawy | C21: =_xlfn.XLOOKUP(B21,'Customer Receivables'!A:A,'Customer Receivables'!B:B," ") -> C-002 | D21: -1650 | E21: عدد 6 عروق 3 متر
